haoda/__init__.py
haoda/util.py
haoda/backend/__init__.py
haoda/backend/common.py
haoda/backend/xilinx.py
haoda/ir/__init__.py
haoda/ir/core.py
haoda/ir/type.py
haoda/ir/visitor.py
haoda/ir/arithmetic/__init__.py
haoda/ir/arithmetic/base.py
haoda/report/__init__.py
haoda/report/xilinx/__init__.py
haoda/report/xilinx/hls.py
haoda/report/xilinx/rtl/__init__.py
haoda/report/xilinx/rtl/generator.py
haoda/report/xilinx/rtl/parser.py
haoda-0.0.20240228.dev1.dist-info/LICENSE
haoda-0.0.20240228.dev1.dist-info/METADATA
haoda-0.0.20240228.dev1.dist-info/WHEEL
haoda-0.0.20240228.dev1.dist-info/top_level.txt
haoda-0.0.20240228.dev1.dist-info/RECORD
