Metadata-Version: 2.1
Name: haoda
Version: 0.0.20240228.dev1
Summary: Hardware-aware optimization and design automation
Home-page: https://github.com/Blaok/haoda
Author: Blaok Chi
Classifier: Development Status :: 2 - Pre-Alpha
Classifier: Intended Audience :: Developers
Classifier: Intended Audience :: Science/Research
Classifier: License :: OSI Approved :: MIT License
Classifier: Programming Language :: Python :: 3 :: Only
Classifier: Programming Language :: Python :: 3
Classifier: Programming Language :: Python :: 3.6
Classifier: Programming Language :: Python :: 3.7
Classifier: Programming Language :: Python :: 3.8
Classifier: Topic :: System :: Hardware
Requires-Python: >=3.6
License-File: LICENSE
Requires-Dist: absl-py
Requires-Dist: cached-property
